sakharniySS/__init__.py
sakharniySS/FeatureExt/FeatureExtraction.py
sakharniySS/FeatureExt/__init__.py
sakharniySS/HyperOpt/HyperOpt.py
sakharniySS/HyperOpt/__init__.py
sakharniySS/Validation/Validation.py
sakharniySS/Validation/__init__.py
sakharniySS/pointB/__init__.py
sakharniySS/pointB/pointB.py
sakharniySS-2.93.dist-info/METADATA
sakharniySS-2.93.dist-info/WHEEL
sakharniySS-2.93.dist-info/top_level.txt
sakharniySS-2.93.dist-info/RECORD
