Metadata-Version: 2.1
Name: sakharniySS
Version: 2.93
Summary: Combined package for feature extraction, hyperparameter tuning, and validation schema
Home-page: UNKNOWN
Author: Siarhei Sakharnyi
License: UNKNOWN
Platform: UNKNOWN
Requires-Dist: numpy
Requires-Dist: scikit-learn
Requires-Dist: hyperopt
Requires-Dist: pandas
Requires-Dist: fuzzywuzzy
